avcontext/__init__.py
avcontext/avcontext.py
avcontext-0.1.0.dist-info/LICENSE
avcontext-0.1.0.dist-info/METADATA
avcontext-0.1.0.dist-info/WHEEL
avcontext-0.1.0.dist-info/entry_points.txt
avcontext-0.1.0.dist-info/top_level.txt
avcontext-0.1.0.dist-info/RECORD
